dxy/__init__.py
dxy/__main__.py
dxy/torch.py
dxy-1.0.1.dist-info/METADATA
dxy-1.0.1.dist-info/WHEEL
dxy-1.0.1.dist-info/top_level.txt
dxy-1.0.1.dist-info/zip-safe
dxy-1.0.1.dist-info/RECORD
